[
    {
        "id": 52,
        "name": "Meowth",
        "form": "Alola",
        "shadow": false
    },
    {
        "id": 52,
        "name": "Meowth",
        "form": "Galarian",
        "shadow": false
    },
    {
        "id": 53,
        "name": "Persian",
        "form": "Alola",
        "shadow": false
    },
    {
        "id": 77,
        "name": "Ponyta",
        "form": "Normal",
        "shadow": false
    },
    {
        "id": 77,
        "name": "Ponyta",
        "form": "Galarian",
        "shadow": false
    },
    {
        "id": 78,
        "name": "Rapidash",
        "form": "Normal",
        "shadow": false
    },
    {
        "id": 78,
        "name": "Rapidash",
        "form": "Galarian",
        "shadow": false
    },
    {
        "id": 79,
        "name": "Slowpoke",
        "form": "Galarian",
        "shadow": false
    },
    {
        "id": 80,
        "name": "Slowbro",
        "form": "Galarian",
        "shadow": false
    },
    {
        "id": 83,
        "name": "Farfetch\u2019d",
        "form": "Normal",
        "shadow": false
    },
    {
        "id": 83,
        "name": "Farfetch\u2019d",
        "form": "Galarian",
        "shadow": false
    },
    {
        "id": 98,
        "name": "Krabby",
        "form": "Normal",
        "shadow": false
    },
    {
        "id": 99,
        "name": "Kingler",
        "form": "Normal",
        "shadow": false
    },
    {
        "id": 122,
        "name": "Mr. Mime",
        "form": "Normal",
        "shadow": false
    },
    {
        "id": 122,
        "name": "Mr. Mime",
        "form": "Galarian",
        "shadow": false
    },
    {
        "id": 128,
        "name": "Tauros",
        "form": "Paldea_aqua",
        "released": true
    },
    {
        "id": 128,
        "name": "Tauros",
        "form": "Paldea_blaze",
        "released": true
    },
    {
        "id": 128,
        "name": "Tauros",
        "form": "Paldea_combat",
        "released": true
    },
    {
        "id": 140,
        "name": "Kabuto",
        "form": "Normal",
        "shadow": false
    },
    {
        "id": 141,
        "name": "Kabutops",
        "form": "Normal",
        "shadow": false
    },
    {
        "id": 144,
        "name": "Articuno",
        "form": "Galarian",
        "shadow": false
    },
    {
        "id": 145,
        "name": "Zapdos",
        "form": "Galarian",
        "shadow": false
    },
    {
        "id": 146,
        "name": "Moltres",
        "form": "Galarian",
        "shadow": false
    },
    {
        "id": 157,
        "name": "Typhlosion",
        "form": "Hisuian",
        "shadow": false
    },
    {
        "id": 199,
        "name": "Slowking",
        "form": "Galarian",
        "shadow": false
    },
    {
        "id": 222,
        "name": "Corsola",
        "form": "Galarian",
        "released": true
    },
    {
        "id": 263,
        "name": "Zigzagoon",
        "form": "Normal",
        "shadow": false
    },
    {
        "id": 264,
        "name": "Linoone",
        "form": "Normal",
        "shadow": false
    },
    {
        "id": 349,
        "name": "Feebas",
        "form": "Normal",
        "shadow": false
    },
    {
        "id": 350,
        "name": "Milotic",
        "form": "Normal",
        "shadow": false
    },
    {
        "id": 384,
        "name": "Rayquaza",
        "form": "Normal",
        "elite_cm": [
            "Hurricane",
            "Breaking Swipe",
            "Dragon Ascent"
        ]
    },
    {
        "id": 479,
        "name": "Rotom",
        "form": "Heat",
        "released": true
    },
    {
        "id": 483,
        "name": "Dialga",
        "form": "Origin",
        "shadow": false,
        "elite_cm": [
            "Roar of Time"
        ]
    },
    {
        "id": 484,
        "name": "Palkia",
        "form": "Origin",
        "shadow": false,
        "elite_cm": [
            "Spacial Rend"
        ]
    },
    {
        "id": 503,
        "name": "Samurott",
        "form": "Hisuian",
        "shadow": false
    },
    {
        "id": 554,
        "name": "Darumaka",
        "form": "Galarian",
        "shadow": false
    },
    {
        "id": 555,
        "name": "Darmanitan",
        "form": "Galarian_standard",
        "shadow": false
    },
    {
        "id": 555,
        "name": "Darmanitan",
        "form": "Galarian_zen",
        "shadow": false
    },
    {
        "id": 555,
        "name": "Darmanitan",
        "form": "Zen",
        "shadow": false
    },
    {
        "id": 562,
        "name": "Yamask",
        "form": "Normal",
        "shadow": false
    },
    {
        "id": 562,
        "name": "Yamask",
        "form": "Galarian",
        "shadow": false
    },
    {
        "id": 563,
        "name": "Cofagrigus",
        "form": "Normal",
        "shadow": false
    },
    {
        "id": 618,
        "name": "Stunfisk",
        "form": "Normal",
        "shadow": false
    },
    {
        "id": 618,
        "name": "Stunfisk",
        "form": "Galarian",
        "shadow": false
    },
    {
        "id": 646,
        "name": "Kyurem",
        "form": "Black",
        "released": true,
        "elite_cm": [
            "Freeze Shock"
        ]
    },
    {
        "id": 646,
        "name": "Kyurem",
        "form": "White",
        "released": true,
        "elite_cm": [
            "Ice Burn"
        ]
    },
    {
        "id": 649,
        "name": "Genesect",
        "form": "Normal",
        "elite_cm": [
            "Techno Blast Normal"
        ]
    },
    {
        "id": 749,
        "name": "Mudbray",
        "form": "Normal",
        "released": true
    },
    {
        "id": 750,
        "name": "Mudsdale",
        "form": "Normal",
        "released": true
    },
    {
        "id": 781,
        "name": "Dhelmise",
        "form": "Normal",
        "released": true
    },
    {
        "id": 800,
        "name": "Necrozma",
        "form": "Normal",
        "released": true
    },
    {
        "id": 800,
        "name": "Necrozma",
        "form": "Dawn_wings",
        "released": true,
        "elite_cm": [
            "Moongeist Beam"
        ]
    },
    {
        "id": 800,
        "name": "Necrozma",
        "form": "Dusk_mane",
        "released": true,
        "elite_cm": [
            "Sunsteel Strike"
        ]
    },
    {
        "id": 802,
        "name": "Marshadow",
        "form": "Normal",
        "released": true
    },
    {
        "id": 804,
        "name": "Naganadel",
        "form": "Normal",
        "released": true
    },
    {
        "id": 805,
        "name": "Stakataka",
        "form": "Normal",
        "released": true
    },
    {
        "id": 806,
        "name": "Blacephalon",
        "form": "Normal",
        "released": true
    },
    {
        "id": 810,
        "name": "Grookey",
        "form": "Normal",
        "released": true
    },
    {
        "id": 811,
        "name": "Thwackey",
        "form": "Normal",
        "released": true
    },
    {
        "id": 812,
        "name": "Rillaboom",
        "form": "Normal",
        "released": true
    },
    {
        "id": 813,
        "name": "Scorbunny",
        "form": "Normal",
        "released": true
    },
    {
        "id": 814,
        "name": "Raboot",
        "form": "Normal",
        "released": true
    },
    {
        "id": 815,
        "name": "Cinderace",
        "form": "Normal",
        "released": true
    },
    {
        "id": 816,
        "name": "Sobble",
        "form": "Normal",
        "released": true
    },
    {
        "id": 817,
        "name": "Drizzile",
        "form": "Normal",
        "released": true
    },
    {
        "id": 818,
        "name": "Inteleon",
        "form": "Normal",
        "released": true
    },
    {
        "id": 821,
        "name": "Rookidee",
        "form": "Normal",
        "released": true
    },
    {
        "id": 822,
        "name": "Corvisquire",
        "form": "Normal",
        "released": true
    },
    {
        "id": 823,
        "name": "Corviknight",
        "form": "Normal",
        "released": true
    },
    {
        "id": 827,
        "name": "Nickit",
        "form": "Normal",
        "released": true
    },
    {
        "id": 828,
        "name": "Thievul",
        "form": "Normal",
        "released": true
    },
    {
        "id": 829,
        "name": "Gossifleur",
        "form": "Normal",
        "released": true
    },
    {
        "id": 830,
        "name": "Eldegoss",
        "form": "Normal",
        "released": true
    },
    {
        "id": 840,
        "name": "Applin",
        "form": "Normal",
        "released": true
    },
    {
        "id": 841,
        "name": "Flapple",
        "form": "Normal",
        "released": true
    },
    {
        "id": 842,
        "name": "Appletun",
        "form": "Normal",
        "released": true
    },
    {
        "id": 848,
        "name": "Toxel",
        "form": "Normal",
        "released": true
    },
    {
        "id": 849,
        "name": "Toxtricity",
        "form": "Normal",
        "released": true
    },
    {
        "id": 849,
        "name": "Toxtricity",
        "form": "Amped",
        "released": true
    },
    {
        "id": 849,
        "name": "Toxtricity",
        "form": "Low_key",
        "released": true
    },
    {
        "id": 850,
        "name": "Sizzlipede",
        "form": "Normal",
        "released": true
    },
    {
        "id": 851,
        "name": "Centiskorch",
        "form": "Normal",
        "released": true
    },
    {
        "id": 854,
        "name": "Sinistea",
        "form": "Normal",
        "released": true
    },
    {
        "id": 854,
        "name": "Sinistea",
        "form": "Antique",
        "released": true
    },
    {
        "id": 854,
        "name": "Sinistea",
        "form": "Phony",
        "released": true
    },
    {
        "id": 855,
        "name": "Polteageist",
        "form": "Normal",
        "released": true
    },
    {
        "id": 855,
        "name": "Polteageist",
        "form": "Antique",
        "released": true
    },
    {
        "id": 855,
        "name": "Polteageist",
        "form": "Phony",
        "released": true
    },
    {
        "id": 856,
        "name": "Hatenna",
        "form": "Normal",
        "released": true
    },
    {
        "id": 857,
        "name": "Hattrem",
        "form": "Normal",
        "released": true
    },
    {
        "id": 858,
        "name": "Hatterene",
        "form": "Normal",
        "released": true
    },
    {
        "id": 863,
        "name": "Perrserker",
        "form": "Normal",
        "shadow": false
    },
    {
        "id": 864,
        "name": "Cursola",
        "form": "Normal",
        "released": true
    },
    {
        "id": 865,
        "name": "Sirfetch\u2019d",
        "form": "Normal",
        "shadow": false
    },
    {
        "id": 866,
        "name": "Mr. Rime",
        "form": "Normal",
        "shadow": false
    },
    {
        "id": 867,
        "name": "Runerigus",
        "form": "Normal",
        "shadow": false
    },
    {
        "id": 874,
        "name": "Stonjourner",
        "form": "Normal",
        "released": true
    },
    {
        "id": 877,
        "name": "Morpeko",
        "form": "Normal",
        "released": true
    },
    {
        "id": 877,
        "name": "Morpeko",
        "form": "Full_belly",
        "released": true
    },
    {
        "id": 877,
        "name": "Morpeko",
        "form": "Hangry",
        "released": true
    },
    {
        "id": 885,
        "name": "Dreepy",
        "form": "Normal",
        "released": true
    },
    {
        "id": 886,
        "name": "Drakloak",
        "form": "Normal",
        "released": true
    },
    {
        "id": 887,
        "name": "Dragapult",
        "form": "Normal",
        "released": true
    },
    {
        "id": 891,
        "name": "Kubfu",
        "form": "Normal",
        "released": true
    },
    {
        "id": 924,
        "name": "Tandemaus",
        "form": "Normal",
        "released": true
    },
    {
        "id": 925,
        "name": "Maushold",
        "form": "Normal",
        "released": true
    },
    {
        "id": 925,
        "name": "Maushold",
        "form": "Family_of_four",
        "released": true
    },
    {
        "id": 925,
        "name": "Maushold",
        "form": "Family_of_three",
        "released": true
    },
    {
        "id": 926,
        "name": "Fidough",
        "form": "Normal",
        "released": true
    },
    {
        "id": 927,
        "name": "Dachsbun",
        "form": "Normal",
        "released": true
    },
    {
        "id": 944,
        "name": "Shroodle",
        "form": "Normal",
        "released": true
    },
    {
        "id": 945,
        "name": "Grafaiai",
        "form": "Normal",
        "released": true
    },
    {
        "id": 957,
        "name": "Tinkatink",
        "form": "Normal",
        "released": true
    },
    {
        "id": 958,
        "name": "Tinkatuff",
        "form": "Normal",
        "released": true
    },
    {
        "id": 959,
        "name": "Tinkaton",
        "form": "Normal",
        "released": true
    },
    {
        "id": 960,
        "name": "Wiglett",
        "form": "Normal",
        "released": true
    },
    {
        "id": 961,
        "name": "Wugtrio",
        "form": "Normal",
        "released": true
    }
]
